zephyr_core/__init__.py
zephyr_core/actions.py
zephyr_core/constants.py
zephyr_core/core_logger.py
zephyr_core/create_test_cycles.py
zephyr_core/json_treatment.py
zephyr_core/run_json_treatment.py
zephyr_core/run_test_cycle.py
zephyr_core/run_update_test_case.py
zephyr_core/update_test_case.py
zephyr_core/utils.py
zephyr_library-1.0.7.data/scripts/zephyr-core-setup
zephyr_library-1.0.7.dist-info/METADATA
zephyr_library-1.0.7.dist-info/WHEEL
zephyr_library-1.0.7.dist-info/entry_points.txt
zephyr_library-1.0.7.dist-info/top_level.txt
zephyr_library-1.0.7.dist-info/RECORD
